listmakerkpanger882/__init__.py
listmakerkpanger882/list_maker.py
listmakerkpanger882-0.0.2.dist-info/LICENSE
listmakerkpanger882-0.0.2.dist-info/METADATA
listmakerkpanger882-0.0.2.dist-info/WHEEL
listmakerkpanger882-0.0.2.dist-info/top_level.txt
listmakerkpanger882-0.0.2.dist-info/RECORD
