Metadata-Version: 2.1
Name: listmakerkpanger882
Version: 0.0.2
Summary: a test package for checking dependency resolvers
Author: EldritchToast
Author-email: <kpanger88@gmail.com>
Keywords: python,dependency,test,list
Classifier: Development Status :: 1 - Planning
Classifier: Intended Audience :: Developers
Classifier: Programming Language :: Python :: 3
Classifier: Operating System :: Unix
Classifier: Operating System :: MacOS :: MacOS X
Classifier: Operating System :: Microsoft :: Windows
License-File: LICENSE
